{"is_source_file": true, "format": "JavaScript (JSX)", "description": "React component definitions for a carousel UI, including context, hooks, and various carousel elements such as items and navigation buttons.", "external_files": ["react", "embla-carousel-react", "lucide-react", "@/lib/utils", "@/components/ui/button"], "external_methods": ["React.createContext", "React.useContext", "React.useState", "React.useCallback", "React.useEffect", "React.forwardRef"], "published": ["Carousel", "CarouselContent", "CarouselItem", "CarouselPrevious", "CarouselNext"], "classes": [], "methods": [{"name": "useCarousel", "description": "Custom hook to access carousel context, throws error if used outside Carousel component."}], "calls": ["React.createContext", "React.useContext", "React.useState", "React.useCallback", "React.useEffect", "React.forwardRef", "useEmblaCarousel", "cn", "Button", "api.canScrollPrev", "api.canScrollNext", "api.scrollPrev", "api.scrollNext", "api.on", "api.off"], "search-terms": ["Carousel React component", "embla-carousel integration", "carousel navigation buttons", "carousel context hook", "jsx carousel component"], "state": 2, "ctags": [], "filename": "frontend/src/components/ui/carousel.jsx", "format-version": 4, "code-base-name": "https://github.com/kavia-common/vidartemp-241505.git:kavia-main-4624", "knowledge_revision": 39, "git_revision": "b258f4756ef92f0668602952c46bbee54f538ebe", "revision_history": [{"39": "b258f4756ef92f0668602952c46bbee54f538ebe"}]}